async_tensorart/__init__.py
async_tensorart/__version__.py
async_tensorart/base.py
async_tensorart/client.py
async_tensorart/exceptions.py
async_tensorart/py.typed
async_tensorart/signature.py
async_tensorart/structs/__init__.py
async_tensorart/structs/jobs/__init__.py
async_tensorart/structs/jobs/delete/__init__.py
async_tensorart/structs/jobs/delete/job.py
async_tensorart/structs/jobs/get/__init__.py
async_tensorart/structs/jobs/get/job.py
async_tensorart/structs/jobs/get/stage.py
async_tensorart/structs/jobs/get/status.py
async_tensorart/structs/jobs/post/__init__.py
async_tensorart/structs/jobs/post/animate_diff.py
async_tensorart/structs/jobs/post/control_net.py
async_tensorart/structs/jobs/post/diffusion_input.py
async_tensorart/structs/jobs/post/enums.py
async_tensorart/structs/jobs/post/image_to_adetailer.py
async_tensorart/structs/jobs/post/image_to_inpaint.py
async_tensorart/structs/jobs/post/image_to_upscaler.py
async_tensorart/structs/jobs/post/job.py
async_tensorart/structs/jobs/post/lora.py
async_tensorart/structs/jobs/post/stage.py
async_tensorart/structs/models/__init__.py
async_tensorart/structs/models/model.py
async_tensorart/utils/__init__.py
async_tensorart/utils/msgspec_helpers.py
async_tensorart-0.2.1.dist-info/LICENSE
async_tensorart-0.2.1.dist-info/METADATA
async_tensorart-0.2.1.dist-info/WHEEL
async_tensorart-0.2.1.dist-info/RECORD
