Metadata-Version: 2.1
Name: async-tensorart
Version: 0.2.1
Summary: Asyncio wrapper for TensorArt API
License: MIT
Keywords: api,framework,wrapper,asyncio,tensorart
Author: andrew000
Requires-Python: >=3.10
Classifier: License :: OSI Approved :: MIT License
Classifier: Programming Language :: Python :: 3
Classifier: Programming Language :: Python :: 3.10
Classifier: Programming Language :: Python :: 3.11
Classifier: Programming Language :: Python :: 3.12
Requires-Dist: aiohttp (>=3.8,<4)
Requires-Dist: cryptography (>=41.0,<44)
Requires-Dist: msgspec (>=0.18,<0.19)
Project-URL: Bug Tracker, https://github.com/andrew000/AsyncTensorArt/issues
Project-URL: homepage, https://github.com/andrew000/AsyncTensorArt
Project-URL: repository, https://github.com/andrew000/AsyncTensorArt
